bygeon/__init__.py
bygeon/__main__.py
bygeon/hub.py
bygeon/main.py
bygeon/message.py
bygeon/util.py
bygeon/messenger/__init__.py
bygeon/messenger/cqhttp.py
bygeon/messenger/discord.py
bygeon/messenger/messenger.py
bygeon/messenger/slack.py
bygeon/messenger/definition/__init__.py
bygeon/messenger/definition/cqhttp.py
bygeon/messenger/definition/discord.py
bygeon/messenger/definition/slack.py
bygeon-0.0.9.dist-info/LICENSE
bygeon-0.0.9.dist-info/METADATA
bygeon-0.0.9.dist-info/WHEEL
bygeon-0.0.9.dist-info/entry_points.txt
bygeon-0.0.9.dist-info/top_level.txt
bygeon-0.0.9.dist-info/RECORD
