Metadata-Version: 2.1
Name: bygeon
Version: 0.0.9
Summary: A simple tool for syncing messages between multiple IMs
Author-email: dummyx <pygeon@gmx.com>
License: AGPL-3.0-only
Project-URL: Homepage, https://github.com/dummyx/bygeon
Project-URL: Bug Tracker, https://github.com/dummyx/bygeon/issues
Classifier: Programming Language :: Python :: 3.10
Classifier: License :: OSI Approved :: GNU Affero General Public License v3
Classifier: Operating System :: Unix
Requires-Python: >=3.10
License-File: LICENSE
Requires-Dist: colorlog (>=6.6.0)
Requires-Dist: requests (>=2.28.1)
Requires-Dist: tomli (>=2.0.1)
Requires-Dist: websocket-client (>=1.3.3)
Requires-Dist: PyPika (>=0.48.9)
Requires-Dist: orjson (>=3.7.7)
Requires-Dist: typing-extensions (>=4.3.0)
